hdl/load_unit.sv
module load_unit(
    input  [31:0] mem_input,
    input  [2:0]  funct3,

    output [31:0] result
);

wire [31:0] signed_byte = {{24{mem_input[7]}}, mem_input[7:0]};
wire [31:0] signed_half = {{16{mem_input[15]}}, mem_input[15:0]};
wire [31:0] unsigned_byte = {{24{1'b0}}, mem_input[7:0]};
wire [31:0] unsigned_half = {{16{1'b0}}, mem_input[15:0]};

assign result = funct3 == 3'h0 ? signed_byte :
               (funct3 == 3'h1 ? signed_half :
               (funct3 == 3'h2 ? mem_input :
               (funct3 == 3'h4 ? unsigned_byte :
               (funct3 == 3'h5 ? unsigned_half : 0))));

endmodule

hdl/branch_unit.sv
module branch_unit(
    input signed [31:0] rs1,
    input signed [31:0] rs2,
    input [2:0] funct3,
    
    output result
);

wire unsigned [31:0] rs1_unsigned = rs1;
wire unsigned [31:0] rs2_unsigned = rs2;

assign result = funct3 == 3'h0 ? rs1          == rs2 :
               (funct3 == 3'h1 ? rs1          != rs2 :
               (funct3 == 3'h4 ? rs1          <  rs2 :
               (funct3 == 3'h5 ? rs1          >= rs2 :
               (funct3 == 3'h6 ? rs1_unsigned <  rs2_unsigned :
               (funct3 == 3'h7 ? rs1_unsigned >= rs2_unsigned : 0)))));

endmodule

hdl/alu.sv
module alu (
    input [31:0] rs1,
    input [31:0] rs2,
    input [11:0] imm,
    input imm_select,
    input [2:0] funct3,
    input [6:0] funct7,

    output [31:0] result
);

wire [31:0] imm_msbextend = { {20{imm[11]}},imm[11:0]};
wire [31:0] imm_zeroextend = { {20{1'b0}}, imm[11:0]};

wire [31:0] operand = imm_select ? imm_msbextend : rs2;

wire signed [31:0] rs1_signed = rs1;
wire signed [31:0] operand_signed = operand;

wire [31:0] add_res = rs1 + operand;
wire [31:0] sub_res = rs1 - operand;
wire [31:0] xor_res = rs1 ^ operand;
wire [31:0] or_res  = rs1 | operand;
wire [31:0] and_res = rs1 & operand;
wire [31:0] sll_res = rs1 << operand[4:0];
wire [31:0] srl_res = rs1 >> operand[4:0];
wire [31:0] sra_res = rs1_signed >> operand[4:0];
wire [31:0] slt_res = rs1_signed < operand_signed ? 1 : 0;
wire [31:0] sltu_res = rs1 < imm_zeroextend ? 1 : 0;

wire [31:0] add_sub = !imm_select && funct7 == 7'h20 ? sub_res : add_res;
wire [31:0] sll_sra = funct7 == 7'h20 ? sra_res : srl_res;

assign result = funct3 == 3'h0 ? add_sub :
               (funct3 == 3'h4 ? xor_res :
               (funct3 == 3'h6 ? or_res  :
               (funct3 == 3'h7 ? and_res :
               (funct3 == 3'h1 ? sll_res :
               (funct3 == 3'h5 ? sll_sra :
               (funct3 == 3'h2 ? slt_res :
               (sltu_res)))))));

endmodule

hdl/crabcore.sv
module crabcore(
    input clk,
    input reset,

    output reg mem_addr_valid,
    output reg [31:0] mem_addr,

    output reg mem_data_valid,
    output reg [31:0] mem_data,

    input mem_ready,
    input [31:0] mem_input,
    input mem_write_done,

    output reg [2:0] io_mode,
    output reg mem_ack,

    output [31:0] registers_debug [31:0],
    output [31:0] pc_debug,
    output [4:0] core_state_debug
);


wire [31:0] register_out [31:0];
reg [31:0] registers [31:0];
reg [31:0] program_counter;
reg [31:0] loaded_instruction;

wire [31:0] current_instruction = core_state == FETCH_STATE ? mem_input : loaded_instruction;

integer i;
genvar c;

for (c = 1; c < 32; c++) begin
    assign register_out[c] = registers[c];
end

assign register_out[0] = 0;
assign pc_debug[31:0] = program_counter;

for (c = 0; c < 32; c++)
    assign registers_debug[c] = register_out[c];

wire [31:0] ra = register_out[1];
wire [31:0] sp = register_out[2];
wire [31:0] gp = register_out[3];
wire [31:0] tp = register_out[4];
wire [31:0] a0 = register_out[10];
wire [31:0] a1 = register_out[11];


localparam OP_IMM_ARITHM =    7'b0010011;
localparam OP_REG_ARITHM =    7'b0110011;
localparam OP_IMM_LOAD   =    7'b0000011;
localparam OP_STORE =         7'b0100011;
localparam OP_BRANCH =        7'b1100011;
localparam OP_JUMP =          7'b1101111;
localparam OP_JUMP_REG =      7'b1100111;
localparam OP_LOAD_UPPER =    7'b0110111;
localparam OP_LOAD_UPPER_PC = 7'b0010111;
localparam OP_CONTROL_STATUS = 7'b1110011;

wire [6:0] opcode = current_instruction[6:0];
wire [4:0] rd = current_instruction[11:7];
wire [2:0] funct3 = current_instruction[14:12];
wire [6:0] funct7 = current_instruction[31:25];
wire [4:0] rs1 = current_instruction[19:15];
wire [4:0] rs2 = current_instruction[24:20];
wire [11:0] i_immediate = current_instruction[31:20];
wire [11:0] s_immediate = {current_instruction[31:25], current_instruction[11:7]};

wire [12:0] b_immediate;
assign b_immediate[12] = current_instruction[31];
assign b_immediate[11] = current_instruction[7];
assign b_immediate[10:5] = current_instruction[30:25];
assign b_immediate[4:1] = current_instruction[11:8];
assign b_immediate[0] = 0;
wire [31:0] b_imm_extended = {{19{b_immediate[12]}}, b_immediate[12:1], 1'b0};

wire [20:0] j_immediate;
assign j_immediate[20] = current_instruction[31];
assign j_immediate[10:1] = current_instruction[30:21];
assign j_immediate[11] = current_instruction[20];
assign j_immediate[19:12] = current_instruction[19:12];
assign j_immediate[0] = 0;

wire [19:0] u_immediate = current_instruction[31:12];
wire [31:0] u_imm_shifted = {u_immediate, {12{1'b0}}};

wire [31:0] rs1_register = register_out[rs1];
wire [31:0] rs2_register = register_out[rs2];

reg [31:0] rs1_register_alu;
reg [31:0] rs2_register_alu;
reg [2:0]  funct3_alu;
reg [6:0]  funct7_alu;
reg [11:0] imm_alu;

reg imm_select;
wire [31:0] alu_result;
wire branch_result;

wire [31:0] load_result;

alu alu1(.rs1(rs1_register_alu), .rs2(rs2_register_alu), .imm(imm_alu),
         .imm_select(imm_select), .funct3(funct3_alu), .funct7(funct7_alu),
         .result(alu_result));

branch_unit bu1(.rs1(rs1_register), .rs2(rs2_register), .funct3(funct3),
                .result(branch_result));

load_unit lu1(.mem_input(mem_input), .funct3(funct3), .result(load_result));

reg [3:0] core_state;

assign core_state_debug[4:0] = core_state;

localparam FETCH_STATE = 0;
localparam EXECUTE_STATE = 1;
localparam BRANCH_STATE = 2;
localparam LOAD_STATE = 3;
localparam AFTERLOAD_STATE = 4;
localparam STORE_STATE = 5;
localparam JUMP_STATE = 6;
localparam ULOAD_STATE = 7;
localparam IGNORE_STATE = 8;

always @(posedge clk) begin
    if (reset) begin
        for (i = 1; i < 32; i++)
            registers[i] <= 0;
        core_state <= FETCH_STATE;
        mem_ack <= 0;
        program_counter = 0;
        mem_addr <= 0;
        mem_addr_valid <= 1;
    end else begin
        if (core_state == FETCH_STATE && mem_ready) begin
            loaded_instruction = mem_input;
            mem_ack <= !mem_ack;
            mem_addr_valid <= 0;
            case (opcode)
                OP_IMM_ARITHM : begin
                    rs1_register_alu <= rs1_register;
                    imm_alu <= i_immediate;
                    imm_select <= 1;
                    funct3_alu <= funct3;
                    funct7_alu <= funct7;
                    core_state <= EXECUTE_STATE;
                end
                OP_REG_ARITHM : begin
                    rs1_register_alu <= rs1_register;
                    rs2_register_alu <= rs2_register;
                    imm_select <= 0;
                    funct3_alu <= funct3;
                    funct7_alu <= funct7;
                    core_state <= EXECUTE_STATE;
                end
                OP_BRANCH : begin
                    rs1_register_alu <= program_counter;
                    rs2_register_alu <= b_imm_extended;
                    imm_select <= 0;
                    funct3_alu <= 0;
                    funct7_alu <= 0;
                    core_state <= BRANCH_STATE;
                end
                OP_IMM_LOAD : begin
                    mem_addr <= rs1_register + i_immediate;
                    mem_addr_valid <= 1;
                    core_state <= LOAD_STATE;
                end
                OP_STORE : begin
                    mem_addr <= rs1_register + s_immediate;
                    mem_addr_valid <= 1;
                    mem_data <= rs2_register;
                    io_mode <= funct3;
                    mem_data_valid <= 1;
                    core_state <= STORE_STATE;
                end
                OP_JUMP : begin
                    rs1_register_alu <= program_counter + 4;
                    core_state <= JUMP_STATE;
                end
                OP_JUMP_REG : begin
                    rs1_register_alu <= program_counter + 4;
                    core_state <= JUMP_STATE;
                end
                OP_LOAD_UPPER : begin
                    core_state <= ULOAD_STATE;
                end
                OP_LOAD_UPPER_PC : begin
                    core_state <= ULOAD_STATE;
                end
                OP_CONTROL_STATUS : begin
                    if (i_immediate == 12'hf14)
                        rs1_register_alu <= 0;
                    else if (i_immediate == 12'h342)
                        rs1_register_alu <= 0;
                    else
                        rs1_register_alu <= i_immediate;
                    rs2_register_alu <= 0;
                    imm_select <= 0;
                    funct3_alu <= 0;
                    funct7_alu <= 0;
                    core_state <= EXECUTE_STATE;
                end
                default : begin
                    core_state <= IGNORE_STATE;
                end
            endcase
        end else if (core_state == LOAD_STATE && mem_ready) begin
            registers[rd] <= load_result;
            mem_ack <= !mem_ack;
            core_state <= AFTERLOAD_STATE;
        end
    end
end

always @(negedge clk) begin
    if (reset) begin
        for (i = 1; i < 32; i++)
            registers[i] <= 0;
        core_state <= FETCH_STATE;
        mem_ack <= 0;
        program_counter = 0;
        mem_addr <= 0;
        mem_addr_valid <= 1;
    end else begin
        case (core_state)
        EXECUTE_STATE : begin
            registers[rd] <= alu_result;
            core_state <= FETCH_STATE;
            program_counter = program_counter + 4;
            mem_addr <= program_counter;
            mem_addr_valid <= 1;
        end
        BRANCH_STATE : begin
            program_counter = branch_result ? alu_result : program_counter + 4;
            mem_addr <= program_counter;
            core_state <= FETCH_STATE;
            mem_addr_valid <= 1;
        end
        AFTERLOAD_STATE : begin
            program_counter = program_counter + 4;
            mem_addr <= program_counter;
            mem_addr_valid <= 1;
            core_state <= FETCH_STATE;
        end
        STORE_STATE : begin
            if (mem_write_done) begin
                program_counter = program_counter + 4;
                mem_addr <= program_counter;
                mem_addr_valid <= 1;
                mem_data_valid <= 0;
                core_state <= FETCH_STATE;
            end
        end
        JUMP_STATE : begin
            program_counter = OP_JUMP == opcode 
                                ? program_counter + {{10{j_immediate[20]}}, j_immediate}
                                : rs1_register + {{20{i_immediate[11]}}, i_immediate};
            registers[rd] <= rs1_register_alu;
            mem_addr <= program_counter;
            mem_addr_valid <= 1;
            core_state <= FETCH_STATE;
        end
        ULOAD_STATE : begin
            registers[rd] = opcode == OP_LOAD_UPPER
                                ? u_imm_shifted
                                : program_counter + u_imm_shifted;
            program_counter = program_counter + 4;
            mem_addr <= program_counter;
            mem_addr_valid <= 1;
            core_state <= FETCH_STATE;
        end
        IGNORE_STATE : begin
            program_counter = program_counter + 4;
            mem_addr <= program_counter;
            mem_addr_valid <= 1;
            core_state <= FETCH_STATE;
        end
        endcase
    end
        
end

endmodule

hdl/membus.sv
module membus;

reg clk = 0;
reg reset = 0;

reg [31:0] memory_reversed [4096:0];

reg [31:0] memory [4096:0];

wire [31:0] mem_addr;
wire mem_addr_valid;
wire [31:0] mem_data_write;
wire mem_data_write_valid;

reg mem_ready;
reg [31:0] mem_input;

wire [31:0] register_debug[31:0];
wire [31:0] pc_debug;
wire [4:0] core_state_debug;

initial $readmemh("output.hex", memory_reversed);

initial begin
    for (i = 0; i < 4096; i++) begin
        memory[i][7:0] = memory_reversed[i][31:24];
        memory[i][15:8] = memory_reversed[i][23:16];
        memory[i][23:16] = memory_reversed[i][15:8];
        memory[i][31:24] = memory_reversed[i][7:0];
    end
end

integer i;
integer j;

localparam BYTE_IO_MODE = 2'h0;
localparam HALF_IO_MODE = 2'h1;
localparam WORD_IO_MODE = 2'h2;

wire [2:0] io_mode;

reg prev_mem_ack = 0;
wire mem_ack;

reg [2:0] mem_state = IDLE_STATE;

reg mem_write_done = 0;

crabcore core1(.clk(clk), .reset(reset), .mem_addr_valid(mem_addr_valid), .mem_addr(mem_addr),
               .mem_data_valid(mem_data_write_valid), .mem_data(mem_data_write),
               .mem_ready(mem_ready), .mem_input(mem_input), .registers_debug(register_debug),
               .pc_debug(pc_debug), .core_state_debug(core_state_debug), .io_mode(io_mode),
               .mem_write_done(mem_write_done), .mem_ack(mem_ack));

localparam IDLE_STATE = 0;
localparam WRITE_STATE = 1;
localparam READ_STATE = 2;


always @(clk) begin
    if (reset) begin
        mem_state <= IDLE_STATE;
    end
    case (mem_state)
    IDLE_STATE : begin
        if (mem_addr_valid && mem_data_write_valid) begin
            mem_state <= WRITE_STATE;
            case (io_mode)
            WORD_IO_MODE : memory[mem_addr[14:2]] <= mem_data_write;
            HALF_IO_MODE : memory[mem_addr[14:2]][15:0] <= mem_data_write[15:0];
            BYTE_IO_MODE : memory[mem_addr[14:2]][7:0] <= mem_data_write[7:0];
            endcase
            mem_write_done <= 1;
            prev_mem_ack <= mem_ack;
        end else if (mem_addr_valid) begin
            mem_state <= READ_STATE;
            mem_input <= memory[mem_addr[14:2]];
            mem_ready <= 1;
            prev_mem_ack <= mem_ack;
        end
    end
    WRITE_STATE : begin
        if (mem_addr_valid && !mem_data_write_valid) begin
            mem_state <= READ_STATE;
            mem_input <= memory[mem_addr[14:2]];
            mem_ready <= 1;
            prev_mem_ack <= mem_ack;
            mem_write_done <= 0;
        end
    end
    READ_STATE : begin
        if (mem_ack != prev_mem_ack) begin
            mem_write_done <= 0;
            mem_state <= IDLE_STATE;
            mem_ready <= 0;
        end
    end
    endcase
end



initial begin
    $dumpfile("vars.vcd");
    $dumpvars;
    reset <= 1;
    clk <= 1;
    #1;
    clk <= 0;
    #1;
    reset <= 0;
    #1;
    clk <= 0;
    #1;
    for (j = 0; j < 1000; j++) begin
        clk <= !clk;
        $display("clk: %b, PC: %h, state: %d", clk,  pc_debug, core_state_debug);
        for (i = 0; i < 32; i++)
            $display("%d: %d", i, register_debug[i]);
        #1;
    end
end

endmodule

hdl/vars.vcd
$date
	Wed Apr  6 14:14:27 2022
$end
$version
	Icarus Verilog
$end
$timescale
	1s
$end
$scope module membus $end
$var wire 32 ! pc_debug [31:0] $end
$var wire 1 " mem_data_write_valid $end
$var wire 32 # mem_data_write [31:0] $end
$var wire 1 $ mem_addr_valid $end
$var wire 32 % mem_addr [31:0] $end
$var wire 1 & mem_ack $end
$var wire 3 ' io_mode [2:0] $end
$var wire 5 ( core_state_debug [4:0] $end
$var reg 1 ) clk $end
$var reg 32 * mem_input [31:0] $end
$var reg 1 + mem_ready $end
$var reg 3 , mem_state [2:0] $end
$var reg 1 - mem_write_done $end
$var reg 1 . prev_mem_ack $end
$var reg 1 / reset $end
$var integer 32 0 i [31:0] $end
$var integer 32 1 j [31:0] $end
$scope module core1 $end
$var wire 32 2 a0 [31:0] $end
$var wire 32 3 a1 [31:0] $end
$var wire 1 ) clk $end
$var wire 32 4 gp [31:0] $end
$var wire 32 5 mem_input [31:0] $end
$var wire 1 + mem_ready $end
$var wire 1 - mem_write_done $end
$var wire 32 6 pc_debug [31:0] $end
$var wire 32 7 ra [31:0] $end
$var wire 1 / reset $end
$var wire 32 8 rs1_register [31:0] $end
$var wire 32 9 rs2_register [31:0] $end
$var wire 32 : sp [31:0] $end
$var wire 32 ; tp [31:0] $end
$var wire 20 < u_immediate [19:0] $end
$var wire 32 = u_imm_shifted [31:0] $end
$var wire 12 > s_immediate [11:0] $end
$var wire 5 ? rs2 [4:0] $end
$var wire 5 @ rs1 [4:0] $end
$var wire 5 A rd [4:0] $end
$var wire 7 B opcode [6:0] $end
$var wire 32 C load_result [31:0] $end
$var wire 21 D j_immediate [20:0] $end
$var wire 12 E i_immediate [11:0] $end
$var wire 7 F funct7 [6:0] $end
$var wire 3 G funct3 [2:0] $end
$var wire 32 H current_instruction [31:0] $end
$var wire 5 I core_state_debug [4:0] $end
$var wire 1 J branch_result $end
$var wire 13 K b_immediate [12:0] $end
$var wire 32 L b_imm_extended [31:0] $end
$var wire 32 M alu_result [31:0] $end
$var reg 4 N core_state [3:0] $end
$var reg 3 O funct3_alu [2:0] $end
$var reg 7 P funct7_alu [6:0] $end
$var reg 12 Q imm_alu [11:0] $end
$var reg 1 R imm_select $end
$var reg 3 S io_mode [2:0] $end
$var reg 32 T loaded_instruction [31:0] $end
$var reg 1 & mem_ack $end
$var reg 32 U mem_addr [31:0] $end
$var reg 1 $ mem_addr_valid $end
$var reg 32 V mem_data [31:0] $end
$var reg 1 " mem_data_valid $end
$var reg 32 W program_counter [31:0] $end
$var reg 32 X rs1_register_alu [31:0] $end
$var reg 32 Y rs2_register_alu [31:0] $end
$var integer 32 Z i [31:0] $end
$scope begin genblk1[1] $end
$upscope $end
$scope begin genblk1[2] $end
$upscope $end
$scope begin genblk1[3] $end
$upscope $end
$scope begin genblk1[4] $end
$upscope $end
$scope begin genblk1[5] $end
$upscope $end
$scope begin genblk1[6] $end
$upscope $end
$scope begin genblk1[7] $end
$upscope $end
$scope begin genblk1[8] $end
$upscope $end
$scope begin genblk1[9] $end
$upscope $end
$scope begin genblk1[10] $end
$upscope $end
$scope begin genblk1[11] $end
$upscope $end
$scope begin genblk1[12] $end
$upscope $end
$scope begin genblk1[13] $end
$upscope $end
$scope begin genblk1[14] $end
$upscope $end
$scope begin genblk1[15] $end
$upscope $end
$scope begin genblk1[16] $end
$upscope $end
$scope begin genblk1[17] $end
$upscope $end
$scope begin genblk1[18] $end
$upscope $end
$scope begin genblk1[19] $end
$upscope $end
$scope begin genblk1[20] $end
$upscope $end
$scope begin genblk1[21] $end
$upscope $end
$scope begin genblk1[22] $end
$upscope $end
$scope begin genblk1[23] $end
$upscope $end
$scope begin genblk1[24] $end
$upscope $end
$scope begin genblk1[25] $end
$upscope $end
$scope begin genblk1[26] $end
$upscope $end
$scope begin genblk1[27] $end
$upscope $end
$scope begin genblk1[28] $end
$upscope $end
$scope begin genblk1[29] $end
$upscope $end
$scope begin genblk1[30] $end
$upscope $end
$scope begin genblk1[31] $end
$upscope $end
$scope begin genblk2[0] $end
$upscope $end
$scope begin genblk2[1] $end
$upscope $end
$scope begin genblk2[2] $end
$upscope $end
$scope begin genblk2[3] $end
$upscope $end
$scope begin genblk2[4] $end
$upscope $end
$scope begin genblk2[5] $end
$upscope $end
$scope begin genblk2[6] $end
$upscope $end
$scope begin genblk2[7] $end
$upscope $end
$scope begin genblk2[8] $end
$upscope $end
$scope begin genblk2[9] $end
$upscope $end
$scope begin genblk2[10] $end
$upscope $end
$scope begin genblk2[11] $end
$upscope $end
$scope begin genblk2[12] $end
$upscope $end
$scope begin genblk2[13] $end
$upscope $end
$scope begin genblk2[14] $end
$upscope $end
$scope begin genblk2[15] $end
$upscope $end
$scope begin genblk2[16] $end
$upscope $end
$scope begin genblk2[17] $end
$upscope $end
$scope begin genblk2[18] $end
$upscope $end
$scope begin genblk2[19] $end
$upscope $end
$scope begin genblk2[20] $end
$upscope $end
$scope begin genblk2[21] $end
$upscope $end
$scope begin genblk2[22] $end
$upscope $end
$scope begin genblk2[23] $end
$upscope $end
$scope begin genblk2[24] $end
$upscope $end
$scope begin genblk2[25] $end
$upscope $end
$scope begin genblk2[26] $end
$upscope $end
$scope begin genblk2[27] $end
$upscope $end
$scope begin genblk2[28] $end
$upscope $end
$scope begin genblk2[29] $end
$upscope $end
$scope begin genblk2[30] $end
$upscope $end
$scope begin genblk2[31] $end
$upscope $end
$scope module alu1 $end
$var wire 32 [ and_res [31:0] $end
$var wire 3 \ funct3 [2:0] $end
$var wire 7 ] funct7 [6:0] $end
$var wire 12 ^ imm [11:0] $end
$var wire 1 R imm_select $end
$var wire 32 _ operand_signed [31:0] $end
$var wire 32 ` or_res [31:0] $end
$var wire 32 a rs1 [31:0] $end
$var wire 32 b rs1_signed [31:0] $end
$var wire 32 c rs2 [31:0] $end
$var wire 32 d xor_res [31:0] $end
$var wire 32 e sub_res [31:0] $end
$var wire 32 f srl_res [31:0] $end
$var wire 32 g sra_res [31:0] $end
$var wire 32 h sltu_res [31:0] $end
$var wire 32 i slt_res [31:0] $end
$var wire 32 j sll_sra [31:0] $end
$var wire 32 k sll_res [31:0] $end
$var wire 32 l result [31:0] $end
$var wire 32 m operand [31:0] $end
$var wire 32 n imm_zeroextend [31:0] $end
$var wire 32 o imm_msbextend [31:0] $end
$var wire 32 p add_sub [31:0] $end
$var wire 32 q add_res [31:0] $end
$upscope $end
$scope module bu1 $end
$var wire 3 r funct3 [2:0] $end
$var wire 32 s rs1 [31:0] $end
$var wire 32 t rs1_unsigned [31:0] $end
$var wire 32 u rs2 [31:0] $end
$var wire 32 v rs2_unsigned [31:0] $end
$var wire 1 J result $end
$upscope $end
$scope module lu1 $end
$var wire 3 w funct3 [2:0] $end
$var wire 32 x mem_input [31:0] $end
$var wire 32 y unsigned_half [31:0] $end
$var wire 32 z unsigned_byte [31:0] $end
$var wire 32 { signed_half [31:0] $end
$var wire 32 | signed_byte [31:0] $end
$var wire 32 } result [31:0] $end
$upscope $end
$upscope $end
$upscope $end
$enddefinitions $end
#0
$dumpvars
bx }
bx |
bx {
b0xxxxxxxx z
b0xxxxxxxxxxxxxxxx y
bx x
bx w
bx v
bx u
bx t
bx s
bx r
bx q
bx p
bx o
b0xxxxxxxxxxxx n
bx m
bx l
bx k
bx j
b0x i
b0x h
bx g
bx f
bx e
bx d
bx c
bx b
bx a
bx `
bx _
bx ^
bx ]
bx \
bx [
b100000 Z
bx Y
bx X
b0 W
bx V
b0 U
bx T
bx S
xR
bx Q
bx P
bx O
b0 N
bx M
bx0 L
bx0 K
xJ
b0 I
bx H
bx G
bx F
bx E
bx0 D
bx C
bx B
bx A
bx @
bx ?
bx >
bx000000000000 =
bx <
b0 ;
b0 :
bx 9
bx 8
b0 7
b0 6
bx 5
b0 4
b0 3
b0 2
bx 1
b1000000000000 0
1/
0.
0-
b0 ,
x+
bx *
1)
b0 (
bx '
0&
b0 %
1$
bx #
x"
b0 !
$end
#1
b11111111111111111111111110110111 C
b11111111111111111111111110110111 }
1J
b100000000000 L
b110111 B
b1 A
b0 G
b0 r
b0 w
b0 F
b0 t
b0 8
b0 s
b0 @
b0 v
b0 9
b0 u
b0 ?
b0 E
b1 >
b100000000000 K
b0 D
b0 =
b0 <
b10110111 H
b11111111111111111111111110110111 |
b10110111 {
b10110111 z
b10110111 y
1+
b10110111 *
b10110111 5
b10110111 x
b10 ,
b100000 Z
0)
#2
0/
#4
b111 (
b111 I
b111 N
0$
1&
b10110111 T
1)
b100000 0
b0 1
#5
b0 (
b0 I
b0 N
1$
b100 %
b100 U
0+
b0 ,
b100 !
b100 6
b100 W
0)
b100000 0
b1 1
#6
b0 L
b1100111 B
b0 A
b1 @
b1000 ?
b1000 E
b0 >
b0 K
b1000000000001000 D
b100000001000000000000000 =
b100000001000 <
b1100111 C
b1100111 }
b100000001000000001100111 H
b1100111 |
b11111111111111111000000001100111 {
b1100111 z
b1000000001100111 y
1.
1+
b100000001000000001100111 *
b100000001000000001100111 5
b100000001000000001100111 x
b10 ,
1)
b100000 0
b10 1
#7
0)
b100000 0
b11 1
#8
bx1xxx `
b0x000 [
b110 (
b110 I
b110 N
b1000 b
b1000 X
b1000 a
0$
0&
b100000001000000001100111 T
1)
b100000 0
b100 1
#9
b0 (
b0 I
b0 N
1$
b1000 %
b1000 U
0+
b0 ,
b1000 !
b1000 6
b1000 W
0)
b100000 0
b101 1
#10
b100000000000 L
b10011 B
b1 A
b0 @
b0 ?
b0 E
b1 >
b100000000000 K
b0 D
b0 =
b0 <
b11111111111111111111111110010011 C
b11111111111111111111111110010011 }
b10010011 H
b11111111111111111111111110010011 |
b10010011 {
b10010011 z
b10010011 y
0.
1+
b10010011 *
b10010011 5
b10010011 x
b10 ,
1)
b100000 0
b110 1
#11
0)
b100000 0
b111 1
#12
b0 M
b0 l
b0 i
b0 j
b0 p
b0 q
b0 e
b0 k
b0 f
b0 g
b0 d
b0 _
b0 m
b0 h
b0 `
b0 [
b1 (
b1 I
b1 N
b0 P
b0 ]
b0 O
b0 \
1R
b0 o
b0 n
b0 Q
b0 ^
b0 b
b0 X
b0 a
0$
1&
b10010011 T
1)
b100000 0
b1000 1
#13
1$
b1100 %
b1100 U
b0 (
b0 I
b0 N
0+
b0 ,
b1100 !
b1100 6
b1100 W
0)
b100000 0
b1001 1
#14
b10 L
b10 A
b10 >
b10 K
b10011 C
b10011 }
b100010011 H
b10011 |
b100010011 {
b10011 z
b100010011 y
1.
1+
b100010011 *
b100010011 5
b100010011 x
b10 ,
1)
b100000 0
b1010 1
#15
0)
b100000 0
b1011 1
#16
b1 (
b1 I
b1 N
0$
0&
b100010011 T
1)
b100000 0
b1100 1
#17
1$
b10000 %
b10000 U
b0 (
b0 I
b0 N
0+
b0 ,
b10000 !
b10000 6
b10000 W
0)
b100000 0
b1101 1
#18
b100000000010 L
b11 A
b11 >
b100000000010 K
b11111111111111111111111110010011 C
b11111111111111111111111110010011 }
b110010011 H
b11111111111111111111111110010011 |
b110010011 {
b10010011 z
b110010011 y
0.
1+
b110010011 *
b110010011 5
b110010011 x
b10 ,
1)
b100000 0
b1110 1
#19
0)
b100000 0
b1111 1
#20
b1 (
b1 I
b1 N
0$
1&
b110010011 T
1)
b100000 0
b10000 1
#21
1$
b10100 %
b10100 U
b0 (
b0 I
b0 N
0+
b0 ,
b10100 !
b10100 6
b10100 W
0)
b100000 0
b10001 1
#22
b100 L
b100 A
b100 >
b100 K
b10011 C
b10011 }
b1000010011 H
b10011 |
b1000010011 {
b10011 z
b1000010011 y
1.
1+
b1000010011 *
b1000010011 5
b1000010011 x
b10 ,
1)
b100000 0
b10010 1
#23
0)
b100000 0
b10011 1
#24
b1 (
b1 I
b1 N
0$
0&
b1000010011 T
1)
b100000 0
b10100 1
#25
1$
b11000 %
b11000 U
b0 (
b0 I
b0 N
0+
b0 ,
b11000 !
b11000 6
b11000 W
0)
b100000 0
b10101 1
#26
b100000000100 L
b101 A
b101 >
b100000000100 K
b11111111111111111111111110010011 C
b11111111111111111111111110010011 }
b1010010011 H
b11111111111111111111111110010011 |
b1010010011 {
b10010011 z
b1010010011 y
0.
1+
b1010010011 *
b1010010011 5
b1010010011 x
b10 ,
1)
b100000 0
b10110 1
#27
0)
b100000 0
b10111 1
#28
b1 (
b1 I
b1 N
0$
1&
b1010010011 T
1)
b100000 0
b11000 1
#29
1$
b11100 %
b11100 U
b0 (
b0 I
b0 N
0+
b0 ,
b11100 !
b11100 6
b11100 W
0)
b100000 0
b11001 1
#30
b110 L
b110 A
b110 >
b110 K
b10011 C
b10011 }
b1100010011 H
b10011 |
b1100010011 {
b10011 z
b1100010011 y
1.
1+
b1100010011 *
b1100010011 5
b1100010011 x
b10 ,
1)
b100000 0
b11010 1
#31
0)
b100000 0
b11011 1
#32
b1 (
b1 I
b1 N
0$
0&
b1100010011 T
1)
b100000 0
b11100 1
#33
1$
b100000 %
b100000 U
b0 (
b0 I
b0 N
0+
b0 ,
b100000 !
b100000 6
b100000 W
0)
b100000 0
b11101 1
#34
b100000000110 L
b111 A
b111 >
b100000000110 K
b11111111111111111111111110010011 C
b11111111111111111111111110010011 }
b1110010011 H
b11111111111111111111111110010011 |
b1110010011 {
b10010011 z
b1110010011 y
0.
1+
b1110010011 *
b1110010011 5
b1110010011 x
b10 ,
1)
b100000 0
b11110 1
#35
0)
b100000 0
b11111 1
#36
b1 (
b1 I
b1 N
0$
1&
b1110010011 T
1)
b100000 0
b100000 1
#37
1$
b100100 %
b100100 U
b0 (
b0 I
b0 N
0+
b0 ,
b100100 !
b100100 6
b100100 W
0)
b100000 0
b100001 1
#38
b1000 L
b1000 A
b1000 >
b1000 K
b10011 C
b10011 }
b10000010011 H
b10011 |
b10000010011 {
b10011 z
b10000010011 y
1.
1+
b10000010011 *
b10000010011 5
b10000010011 x
b10 ,
1)
b100000 0
b100010 1
#39
0)
b100000 0
b100011 1
#40
b1 (
b1 I
b1 N
0$
0&
b10000010011 T
1)
b100000 0
b100100 1
#41
1$
b101000 %
b101000 U
b0 (
b0 I
b0 N
0+
b0 ,
b101000 !
b101000 6
b101000 W
0)
b100000 0
b100101 1
#42
b100000001000 L
b1001 A
b1001 >
b100000001000 K
b11111111111111111111111110010011 C
b11111111111111111111111110010011 }
b10010010011 H
b11111111111111111111111110010011 |
b10010010011 {
b10010011 z
b10010010011 y
0.
1+
b10010010011 *
b10010010011 5
b10010010011 x
b10 ,
1)
b100000 0
b100110 1
#43
0)
b100000 0
b100111 1
#44
b1 (
b1 I
b1 N
0$
1&
b10010010011 T
1)
b100000 0
b101000 1
#45
1$
b101100 %
b101100 U
b0 (
b0 I
b0 N
0+
b0 ,
b101100 !
b101100 6
b101100 W
0)
b100000 0
b101001 1
#46
b1010 L
b1010 A
b1010 >
b1010 K
b10011 C
b10011 }
b10100010011 H
b10011 |
b10100010011 {
b10011 z
b10100010011 y
1.
1+
b10100010011 *
b10100010011 5
b10100010011 x
b10 ,
1)
b100000 0
b101010 1
#47
0)
b100000 0
b101011 1
#48
b1 (
b1 I
b1 N
0$
0&
b10100010011 T
1)
b100000 0
b101100 1
#49
1$
b110000 %
b110000 U
b0 (
b0 I
b0 N
0+
b0 ,
b110000 !
b110000 6
b110000 W
0)
b100000 0
b101101 1
#50
b100000001010 L
b1011 A
b1011 >
b100000001010 K
b11111111111111111111111110010011 C
b11111111111111111111111110010011 }
b10110010011 H
b11111111111111111111111110010011 |
b10110010011 {
b10010011 z
b10110010011 y
0.
1+
b10110010011 *
b10110010011 5
b10110010011 x
b10 ,
1)
b100000 0
b101110 1
#51
0)
b100000 0
b101111 1
#52
b1 (
b1 I
b1 N
0$
1&
b10110010011 T
1)
b100000 0
b110000 1
#53
1$
b110100 %
b110100 U
b0 (
b0 I
b0 N
0+
b0 ,
b110100 !
b110100 6
b110100 W
0)
b100000 0
b110001 1
#54
b1100 L
b1100 A
b1100 >
b1100 K
b10011 C
b10011 }
b11000010011 H
b10011 |
b11000010011 {
b10011 z
b11000010011 y
1.
1+
b11000010011 *
b11000010011 5
b11000010011 x
b10 ,
1)
b100000 0
b110010 1
#55
0)
b100000 0
b110011 1
